MANIFEST.in
README
gdownload.py
setup.py
gdownload/DownloadGarmin.py
gdownload/__init__.py
gdownload/main.py
gdownload.egg-info/PKG-INFO
gdownload.egg-info/SOURCES.txt
gdownload.egg-info/dependency_links.txt
gdownload.egg-info/entry_points.txt
gdownload.egg-info/requires.txt
gdownload.egg-info/top_level.txt