Metadata-Version: 1.1
Name: gdownload
Version: 0.1.1
Summary: Tools for download activities from Garmin Connect.
Home-page: http://github.com/corbamico/Garmin-Connect-Downloader
Author: corbamico
Author-email: corbamico@163.com
License: GPL
Keywords: Garmin Connect
Platform: UNKNOWN
Classifier: Development Status :: 4 - Beta
Classifier: Environment :: Console
Classifier: License :: OSI Approved :: GNU General Public License (GPL)
